aiohttp_csrf/__init__.py
aiohttp_csrf/policy.py
aiohttp_csrf/storage.py
aiohttp_csrf/token_generator.py
aiohttp_csrf_fixed-0.0.3.dist-info/LICENCE
aiohttp_csrf_fixed-0.0.3.dist-info/METADATA
aiohttp_csrf_fixed-0.0.3.dist-info/WHEEL
aiohttp_csrf_fixed-0.0.3.dist-info/top_level.txt
aiohttp_csrf_fixed-0.0.3.dist-info/RECORD
