Metadata-Version: 2.1
Name: aiohttp-csrf-fixed
Version: 0.0.3
Summary: ('CSRF protection for aiohttp.web',)
Home-page: https://github.com/TensorTom/aiohttp-csrf
Author: TensorTom
License: UNKNOWN
Keywords: csrf,xsrf,aiohttp
Platform: UNKNOWN
Classifier: Development Status :: 5 - Production/Stable
Classifier: Intended Audience :: Developers
Classifier: License :: OSI Approved :: MIT License
Classifier: Operating System :: POSIX
Classifier: Operating System :: MacOS :: MacOS X
Classifier: Operating System :: Microsoft :: Windows
Classifier: Programming Language :: Python
Classifier: Programming Language :: Python :: 3
Classifier: Programming Language :: Python :: 3.5
Classifier: Programming Language :: Python :: 3.6
Classifier: Programming Language :: Python :: 3.8
Requires-Dist: aiohttp (>=3.2.0)
Provides-Extra: session
Requires-Dist: aiohttp-session (>=2.4.0) ; extra == 'session'
